[{"name":"Aglona","countryCode":"LV","stateCode":"001"},{"name":"Aizkraukle","countryCode":"LV","stateCode":"002"},{"name":"Aizpute","countryCode":"LV","stateCode":"003"},{"name":"Aknīste","countryCode":"LV","stateCode":"004"},{"name":"Aloja","countryCode":"LV","stateCode":"005"},{"name":"Staicele","countryCode":"LV","stateCode":"005"},{"name":"Alsunga","countryCode":"LV","stateCode":"006"},{"name":"Alūksne","countryCode":"LV","stateCode":"007"},{"name":"Ape","countryCode":"LV","stateCode":"009"},{"name":"Auce","countryCode":"LV","stateCode":"010"},{"name":"Piņķi","countryCode":"LV","stateCode":"012"},{"name":"Baldone","countryCode":"LV","stateCode":"013"},{"name":"Baltinava","countryCode":"LV","stateCode":"014"},{"name":"Balvi","countryCode":"LV","stateCode":"015"},{"name":"Bauska","countryCode":"LV","stateCode":"016"},{"name":"Mūrmuiža","countryCode":"LV","stateCode":"017"},{"name":"Brocēni","countryCode":"LV","stateCode":"018"},{"name":"Carnikava","countryCode":"LV","stateCode":"020"},{"name":"Cesvaine","countryCode":"LV","stateCode":"021"},{"name":"Cēsis","countryCode":"LV","stateCode":"022"},{"name":"Cibla","countryCode":"LV","stateCode":"023"},{"name":"Dagda","countryCode":"LV","stateCode":"024"},{"name":"Daugavpils","countryCode":"LV","stateCode":"025"},{"name":"Dobele","countryCode":"LV","stateCode":"026"},{"name":"Dundaga","countryCode":"LV","stateCode":"027"},{"name":"Lieģi","countryCode":"LV","stateCode":"028"},{"name":"Smārde","countryCode":"LV","stateCode":"029"},{"name":"Ērgļi","countryCode":"LV","stateCode":"030"},{"name":"Garkalne","countryCode":"LV","stateCode":"031"},{"name":"Grobiņa","countryCode":"LV","stateCode":"032"},{"name":"Gulbene","countryCode":"LV","stateCode":"033"},{"name":"Iecava","countryCode":"LV","stateCode":"034"},{"name":"Ikšķile","countryCode":"LV","stateCode":"035"},{"name":"Ilūkste","countryCode":"LV","stateCode":"036"},{"name":"Inčukalns","countryCode":"LV","stateCode":"037"},{"name":"Vangaži","countryCode":"LV","stateCode":"037"},{"name":"Jaunjelgava","countryCode":"LV","stateCode":"038"},{"name":"Jaunpils","countryCode":"LV","stateCode":"040"},{"name":"Tīreļi","countryCode":"LV","stateCode":"041"},{"name":"Jēkabpils","countryCode":"LV","stateCode":"042"},{"name":"Krustpils","countryCode":"LV","stateCode":"042"},{"name":"Kandava","countryCode":"LV","stateCode":"043"},{"name":"Kārsava","countryCode":"LV","stateCode":"044"},{"name":"Kocēni","countryCode":"LV","stateCode":"045"},{"name":"Koknese","countryCode":"LV","stateCode":"046"},{"name":"Krāslava","countryCode":"LV","stateCode":"047"},{"name":"Kuldīga","countryCode":"LV","stateCode":"050"},{"name":"Ķegums","countryCode":"LV","stateCode":"051"},{"name":"Baloži","countryCode":"LV","stateCode":"052"},{"name":"Ķekava","countryCode":"LV","stateCode":"052"},{"name":"Lielvārde","countryCode":"LV","stateCode":"053"},{"name":"Limbaži","countryCode":"LV","stateCode":"054"},{"name":"Līgatne","countryCode":"LV","stateCode":"055"},{"name":"Līvāni","countryCode":"LV","stateCode":"056"},{"name":"Lubāna","countryCode":"LV","stateCode":"057"},{"name":"Ludza","countryCode":"LV","stateCode":"058"},{"name":"Madona","countryCode":"LV","stateCode":"059"},{"name":"Mazsalaca","countryCode":"LV","stateCode":"060"},{"name":"Mālpils","countryCode":"LV","stateCode":"061"},{"name":"Mārupe","countryCode":"LV","stateCode":"062"},{"name":"Naukšēni","countryCode":"LV","stateCode":"064"},{"name":"Nereta","countryCode":"LV","stateCode":"065"},{"name":"Nīca","countryCode":"LV","stateCode":"066"},{"name":"Jumprava","countryCode":"LV","stateCode":"067"},{"name":"Ogre","countryCode":"LV","stateCode":"067"},{"name":"Olaine","countryCode":"LV","stateCode":"068"},{"name":"Ozolnieki","countryCode":"LV","stateCode":"069"},{"name":"Stalbe","countryCode":"LV","stateCode":"070"},{"name":"Pāvilosta","countryCode":"LV","stateCode":"071"},{"name":"Pļaviņas","countryCode":"LV","stateCode":"072"},{"name":"Jaunaglona","countryCode":"LV","stateCode":"073"},{"name":"Preiļi","countryCode":"LV","stateCode":"073"},{"name":"Priekule","countryCode":"LV","stateCode":"074"},{"name":"Priekuļi","countryCode":"LV","stateCode":"075"},{"name":"Rauna","countryCode":"LV","stateCode":"076"},{"name":"Riebiņi","countryCode":"LV","stateCode":"078"},{"name":"Roja","countryCode":"LV","stateCode":"079"},{"name":"Ropaži","countryCode":"LV","stateCode":"080"},{"name":"Rucava","countryCode":"LV","stateCode":"081"},{"name":"Rugāji","countryCode":"LV","stateCode":"082"},{"name":"Pilsrundāle","countryCode":"LV","stateCode":"083"},{"name":"Rūjiena","countryCode":"LV","stateCode":"084"},{"name":"Ainaži","countryCode":"LV","stateCode":"086"},{"name":"Salacgrīva","countryCode":"LV","stateCode":"086"},{"name":"Salaspils","countryCode":"LV","stateCode":"087"},{"name":"Saldus","countryCode":"LV","stateCode":"088"},{"name":"Saulkrasti","countryCode":"LV","stateCode":"089"},{"name":"Engure","countryCode":"LV","stateCode":"090"},{"name":"Tukums","countryCode":"LV","stateCode":"090"},{"name":"Sigulda","countryCode":"LV","stateCode":"091"},{"name":"Skrīveri","countryCode":"LV","stateCode":"092"},{"name":"Skrunda","countryCode":"LV","stateCode":"093"},{"name":"Smiltene","countryCode":"LV","stateCode":"094"},{"name":"Ulbroka","countryCode":"LV","stateCode":"095"},{"name":"Seda","countryCode":"LV","stateCode":"096"},{"name":"Strenči","countryCode":"LV","stateCode":"096"},{"name":"Sabile","countryCode":"LV","stateCode":"097"},{"name":"Stende","countryCode":"LV","stateCode":"097"},{"name":"Talsi","countryCode":"LV","stateCode":"097"},{"name":"Valdemārpils","countryCode":"LV","stateCode":"097"},{"name":"Tērvete","countryCode":"LV","stateCode":"098"},{"name":"Zelmeņi","countryCode":"LV","stateCode":"098"},{"name":"Vaiņode","countryCode":"LV","stateCode":"100"},{"name":"Valka","countryCode":"LV","stateCode":"101"},{"name":"Varakļāni","countryCode":"LV","stateCode":"102"},{"name":"Vecvārkava","countryCode":"LV","stateCode":"103"},{"name":"Vecpiebalga","countryCode":"LV","stateCode":"104"},{"name":"Vecumnieki","countryCode":"LV","stateCode":"105"},{"name":"Piltene","countryCode":"LV","stateCode":"106"},{"name":"Viesīte","countryCode":"LV","stateCode":"107"},{"name":"Viļaka","countryCode":"LV","stateCode":"108"},{"name":"Viļāni","countryCode":"LV","stateCode":"109"},{"name":"Zilupe","countryCode":"LV","stateCode":"110"},{"name":"Jelgava","countryCode":"LV","stateCode":"JEL"},{"name":"Jūrmala","countryCode":"LV","stateCode":"JUR"},{"name":"Karosta","countryCode":"LV","stateCode":"LPX"},{"name":"Liepāja","countryCode":"LV","stateCode":"LPX"},{"name":"Rēzekne","countryCode":"LV","stateCode":"REZ"},{"name":"Bolderaja","countryCode":"LV","stateCode":"RIX"},{"name":"Daugavgrīva","countryCode":"LV","stateCode":"RIX"},{"name":"Jaunciems","countryCode":"LV","stateCode":"RIX"},{"name":"Mežaparks","countryCode":"LV","stateCode":"RIX"},{"name":"Riga","countryCode":"LV","stateCode":"RIX"},{"name":"Ventspils","countryCode":"LV","stateCode":"VEN"},{"name":"Valmiera","countryCode":"LV","stateCode":"VMR"}]