[{"name":"Hithadhoo","countryCode":"MV","stateCode":"01"},{"name":"Meedhoo","countryCode":"MV","stateCode":"01"},{"name":"Naifaru","countryCode":"MV","stateCode":"03"},{"name":"Felidhoo","countryCode":"MV","stateCode":"04"},{"name":"Fonadhoo","countryCode":"MV","stateCode":"05"},{"name":"Dhidhdhoo","countryCode":"MV","stateCode":"07"},{"name":"Veymandoo","countryCode":"MV","stateCode":"08"},{"name":"Muli","countryCode":"MV","stateCode":"12"},{"name":"Ugoofaaru","countryCode":"MV","stateCode":"13"},{"name":"Kudahuvadhoo","countryCode":"MV","stateCode":"17"},{"name":"Kulhudhuffushi","countryCode":"MV","stateCode":"23"},{"name":"Funadhoo","countryCode":"MV","stateCode":"24"},{"name":"Manadhoo","countryCode":"MV","stateCode":"25"},{"name":"Guraidhoo","countryCode":"MV","stateCode":"26"},{"name":"Hulhumale","countryCode":"MV","stateCode":"26"},{"name":"Maafushi","countryCode":"MV","stateCode":"26"},{"name":"Male","countryCode":"MV","stateCode":"26"},{"name":"Viligili","countryCode":"MV","stateCode":"27"},{"name":"Thinadhoo","countryCode":"MV","stateCode":"28"},{"name":"Fuvahmulah","countryCode":"MV","stateCode":"29"},{"name":"Mahibadhoo","countryCode":"MV","stateCode":"SC"}]